wechat_auto/__init__.py
wechat_auto/chat.py
wechat_auto/clipboard.py
wechat_auto/core.py
wechat_auto/listener.py
wechat_auto/logger.py
wechat_auto/sender.py
wechat_auto/utils.py
wechat_auto/window.py
wechat_pc_auto-1.1.2.dist-info/licenses/LICENSE
wechat_pc_auto-1.1.2.dist-info/METADATA
wechat_pc_auto-1.1.2.dist-info/WHEEL
wechat_pc_auto-1.1.2.dist-info/top_level.txt
wechat_pc_auto-1.1.2.dist-info/RECORD
