Metadata-Version: 2.4
Name: wechat-pc-auto
Version: 1.1.2
Summary: Stable WeChat PC automation tool: send messages, files, and auto-reply
Author-email: YourName <your@email.com>
License: MIT
Project-URL: Homepage, https://github.com/yourname/wechat-pc-auto
Project-URL: Repository, https://github.com/yourname/wechat-pc-auto
Project-URL: Issues, https://github.com/yourname/wechat-pc-auto/issues
Keywords: wechat,automation,uiautomation,windows,messaging,auto-reply
Classifier: Programming Language :: Python :: 3
Classifier: License :: OSI Approved :: MIT License
Classifier: Operating System :: Microsoft :: Windows
Requires-Python: >=3.8
License-File: LICENSE
Requires-Dist: uiautomation>=2.0.18
Requires-Dist: pyperclip>=1.8.2
Dynamic: license-file
